Metadata-Version: 2.1
Name: otev-enman
Version: 1.0.0
Summary: OpenSearch manager repository.
Home-page: https://github.com/strvcom/osman
Author: STRV DS Department <datascience.dept@strv.com>
Author-email: datascience.dept@strv.com
Requires-Python: >=3.8
License-File: LICENSE.md
